bsimx/__init__.py
bsimx/static/bundle.js
bsimx/static/style.css
bsimx/templates/index.html
bsimx/type.py
bsimx-0.2.1.dist-info/METADATA
bsimx-0.2.1.dist-info/WHEEL
bsimx-0.2.1.dist-info/RECORD
