Metadata-Version: 2.1
Name: bsimx
Version: 0.2.1
Summary: The agent-based modeling tool with deck.gl, networkx and osmnx.
Author: s-uei
Author-email: uei.shunsuke@kagawa-u.ac.jp
Requires-Python: >=3.10,<4.0
Classifier: Programming Language :: Python :: 3
Classifier: Programming Language :: Python :: 3.10
Classifier: Programming Language :: Python :: 3.11
Requires-Dist: flask (>=2.2.3,<3.0.0)
Requires-Dist: networkx (>=2.8.8,<3.0.0)
Requires-Dist: osmnx (>=1.3.0,<2.0.0)
Requires-Dist: pydantic (>=1.10.9,<2.0.0)
